core1/__init__.py
core1/after.py
core1/before.py
core1/groupby.py
core1-0.0.2.dist-info/METADATA
core1-0.0.2.dist-info/WHEEL
core1-0.0.2.dist-info/entry_points.txt
core1-0.0.2.dist-info/top_level.txt
core1-0.0.2.dist-info/RECORD
